README.rst
setup.py
pyras/__init__.py
pyras.egg-info/PKG-INFO
pyras.egg-info/SOURCES.txt
pyras.egg-info/dependency_links.txt
pyras.egg-info/top_level.txt
pyras/controllers/__init__.py
pyras/controllers/hecras/__init__.py
pyras/controllers/hecras/ras_constants.py
pyras/controllers/hecras/runtime.py
pyras/controllers/hecras/hecrascontroller/__init__.py
pyras/controllers/hecras/hecrascontroller/ras41.py
pyras/controllers/hecras/hecrascontroller/ras500.py
pyras/controllers/hecras/hecrasgeometry/__init__.py
pyras/controllers/hecras/hecrasgeometry/ras41.py
pyras/controllers/hecras/hecrasgeometry/ras500.py
pyras/core/__init__.py
pyras/core/channel.py
pyras/core/structure.py
pyras/core/xsection.py
pyras/io/__init__.py
pyras/io/hecras/__init__.py
pyras/io/hecras/read_ras.py
pyras/io/mike11/__init__.py
pyras/tests/__init__.py
pyras/tools/__init__.py
pyras/tools/units.py
pyras/util/__init__.py