Metadata-Version: 1.1
Name: pyras
Version: 0.2.1
Summary: Python Wrapper of HEC RAS COM interface
Home-page: https://github.com/goanpeca/raspy
Author: Gonzalo Peña-Castellanos
Author-email: goanpeca@gmail.com
License: MIT
Keywords: HEC-RAS HEC RAS controller windows
Platform: UNKNOWN
Classifier: Development Status :: 4 - Beta
Classifier: Environment :: Win32 (MS Windows)
Classifier: License :: OSI Approved :: MIT License
Classifier: Programming Language :: Python :: 2
Classifier: Programming Language :: Python :: 2.7
Classifier: Programming Language :: Python :: 3
Classifier: Programming Language :: Python :: 3.3
Classifier: Programming Language :: Python :: 3.4
Classifier: Topic :: Software Development :: Widget Sets
